max7219LEDMATRIX/__init__.py
max7219LEDMATRIX/font.py
max7219LEDMATRIX/matrix.py
max7219LEDMATRIX-0.0.2.dist-info/METADATA
max7219LEDMATRIX-0.0.2.dist-info/WHEEL
max7219LEDMATRIX-0.0.2.dist-info/top_level.txt
max7219LEDMATRIX-0.0.2.dist-info/RECORD
