Metadata-Version: 2.1
Name: max7219LEDMATRIX
Version: 0.0.2
Summary: This Package contains the code required to drive a max7219 8x8 LED matrix using a Raspberry Pi (with spidev).
Author: Mohammed Varaliya
Author-email: <mohammedvaraliya2661392@gmail.com>
Keywords: Max7219,Led Matrix,Raspberry Pi,8x8 Matrix
Classifier: Development Status :: 5 - Production/Stable
Classifier: Intended Audience :: Developers
Classifier: Programming Language :: Python :: 3
Classifier: Operating System :: Unix
Classifier: Operating System :: MacOS :: MacOS X
Classifier: Operating System :: Microsoft :: Windows
Classifier: Operating System :: POSIX :: Linux
Requires-Dist: spidev
